[{"line":1,"elements":[{"start_timestamp":"2024-02-06T08:24:18.153Z","line":2,"name":"Google search scenario","description":"","id":"this-is-to-do-google-search;google-search-scenario","type":"scenario","keyword":"Scenario","steps":[{"result":{"duration":10733334600,"status":"passed"},"line":3,"name":"user is entering Google.com url in search box","match":{"location":"stepDefinitions.OpenGoogleDefinitions.user_is_entering_google_com_url_in_search_box()"},"keyword":"Given "},{"result":{"duration":251344500,"status":"passed"},"line":4,"name":"user is entering the search term \"trichy\"","match":{"arguments":[{"val":"\"trichy\"","offset":33}],"location":"stepDefinitions.OpenGoogleDefinitions.user_is_entering_the_search_term(java.lang.String)"},"keyword":"When "},{"result":{"duration":385158400,"status":"passed"},"line":5,"name":"presses the Enter key","match":{"location":"stepDefinitions.OpenGoogleDefinitions.presses_the_enter_key()"},"keyword":"And "},{"result":{"duration":10563067600,"status":"passed"},"line":6,"name":"the user should be able to see search results","match":{"location":"stepDefinitions.OpenGoogleDefinitions.the_user_should_be_able_to_see_search_results()"},"keyword":"Then "}]}],"name":"This is to do Google Search","description":"","id":"this-is-to-do-google-search","keyword":"Feature","uri":"file:FeatureFiles/OpenGoogle.feature","tags":[]}]